{
  "version": "6.3.0",
  "flags": {},
  "shapes": [
    {
      "label": "smoke(severe)",
      "points": [
        [
          526.9747899159663,
          391.9327731092437
        ],
        [
          568.1512605042016,
          329.74789915966386
        ],
        [
          556.3865546218486,
          307.05882352941177
        ],
        [
          569.8319327731092,
          292.7731092436975
        ],
        [
          584.1176470588234,
          258.3193277310924
        ],
        [
          577.3949579831932,
          245.71428571428572
        ],
        [
          607.6470588235294,
          218.8235294117647
        ],
        [
          650.5042016806722,
          155.7983193277311
        ],
        [
          641.2605042016806,
          116.30252100840336
        ],
        [
          678.235294117647,
          70.92436974789915
        ],
        [
          690.8403361344538,
          75.12605042016806
        ],
        [
          734.5378151260503,
          3.6974789915966197
        ],
        [
          1108.4873949579833,
          1.176470588235275
        ],
        [
          1013.5294117647057,
          84.36974789915965
        ],
        [
          891.6806722689075,
          144.87394957983193
        ],
        [
          803.4453781512605,
          157.47899159663865
        ],
        [
          700.924369747899,
          252.43697478991598
        ],
        [
          621.9327731092436,
          316.30252100840335
        ],
        [
          612.689075630252,
          428.9075630252101
        ],
        [
          584.1176470588234,
          396.1344537815126
        ],
        [
          592.5210084033613,
          344.03361344537814
        ]
      ],
      "group_id": null,
      "description": "",
      "shape_type": "polygon",
      "flags": {},
      "mask": null
    },
    {
      "label": "smoke(moderate)",
      "points": [
        [
          617.7310924369747,
          426.38655462184875
        ],
        [
          626.9747899159663,
          325.546218487395
        ],
        [
          806.8067226890755,
          164.2016806722689
        ],
        [
          901.7647058823529,
          149.91596638655463
        ],
        [
          1011.0084033613444,
          91.93277310924368
        ],
        [
          1111.8487394957983,
          5.378151260504183
        ],
        [
          1273.1932773109245,
          4.5378151260504005
        ],
        [
          1274.873949579832,
          154.11764705882354
        ],
        [
          1153.0252100840337,
          233.109243697479
        ],
        [
          1030.3361344537816,
          309.5798319327731
        ],
        [
          907.6470588235294,
          357.47899159663865
        ],
        [
          738.7394957983192,
          397.8151260504202
        ],
        [
          717.7310924369747,
          462.52100840336135
        ],
        [
          650.5042016806722,
          461.6806722689076
        ]
      ],
      "group_id": null,
      "description": "",
      "shape_type": "polygon",
      "flags": {},
      "mask": null
    }
  ],
  "imagePath": "frame_43.jpg",
  "imageData": null,
  "imageHeight": 720,
  "imageWidth": 1280
}